sothis
