Metadata-Version: 1.0
Name: sothis
Version: 0.9.6
Summary: a growing library for all things I find use for that is not part of the standard library (to my knowledge)
Home-page: UNKNOWN
Author: Oliver
Author-email: oliverbcontact@gmail.com
License: LICENSE
Platform: UNKNOWN
